Workbook

Sheet START HERE
A1: Lesson 1 Practice. Reliable Workbooks and Modern Formulas
A3: Scenario
A4: You have received a small sales workbook prepared by another analyst. The workbook opens without obvious errors, but several results are unreliable. Repair the model so that it remains correct when assumptions and data change.
A7: Time limit | B7: 30 minutes
A9: # | B9: Task | C9: Instruction | D9: Suggested time | F9: Validation | G9: Expected result | H9: Done
A10: 1 | B10: Workbook architecture | C10: Identify which sheets represent Data, Assumptions, Calculations, and Presentation. | D10: 3 min | F10: Rent Rate | G10: Changing the assumption changes Rent Expense | H10: □
A11: 2 | B11: Remove hard-coded assumption | C11: On Analysis, replace the hard-coded rent percentage with a reference to the Rent Rate assumption. | D11: 3 min | F11: Total Revenue | G11: Includes every Sales row | H11: □
A12: 3 | B12: Repair fragile total | C12: Fix Total Revenue so that it includes all rows and remains correct when new rows are added. | D12: 3 min | F12: Tax | G12: Copies correctly to all rows | H12: □
A13: 4 | B13: Fix reference behavior | C13: Repair the Tax formula so that the tax-rate reference stays fixed when copied down. | D13: 4 min | F13: Lookup | G13: Valid Product IDs return categories | H13: □
A14: 5 | B14: Lookup product attributes | C14: Complete Category using XLOOKUP from the Products table. Keep the unknown Product ID visible as a data-quality issue. | D14: 5 min | F14: Unknown Product | G14: P-999 remains visible | H14: □
A15: 6 | B15: Conditional analysis | C15: Calculate North Revenue with SUMIFS and count transactions above the threshold stored on Assumptions. | D15: 4 min | F15: Aggregation | G15: North Revenue and high-value count are formula-driven | H15: □
A16: 7 | B16: Dynamic output | C16: Create a sorted unique region list and a filtered view of high-value transactions using SORT, UNIQUE, and FILTER. | D16: 5 min | F16: Dynamic arrays | G16: Outputs expand automatically | H16: □
A17: 8 | B17: Readable formula | C17: Rewrite Margin Status using LET with meaningful intermediate variable names. | D17: 3 min | F17: LET | G17: Margin Status uses readable variables | H17: □
A19: Important
A20: Do not judge correctness only by the absence of Excel errors. Several defects in this workbook return plausible numbers.

Sheet Assumptions
A1: Controlled Assumptions
A3: Parameter | B3: Value | C3: Description
A4: Rent Rate | B4: 0.18 | C4: Rent expense as % of revenue
A5: Tax Rate | B5: 0.2 | C5: Tax applied to positive operating profit
A6: High Value Threshold | B6: 10000 | C6: Revenue threshold
A7: Target Margin | B7: 0.25 | C7: Target gross margin

Sheet Products
A1: Product Reference Data
A3: Product ID | B3: Product Name | C3: Category | D3: Unit Cost
A4: P-101 | B4: Basic Laptop | C4: Computers | D4: 620
A5: P-102 | B5: Pro Laptop | C5: Computers | D5: 980
A6: P-103 | B6: Office Monitor | C6: Displays | D6: 190
A7: P-104 | B7: Mechanical Keyboard | C7: Accessories | D7: 58
A8: P-105 | B8: Wireless Mouse | C8: Accessories | D8: 27
A9: P-106 | B9: USB-C Dock | C9: Accessories | D9: 86
A10: P-107 | B10: 27-inch Monitor | C10: Displays | D10: 245
A11: P-108 | B11: Web Camera | C11: Accessories | D11: 44

Sheet Sales
A1: Sales Transactions
A3: Txn ID | B3: Date | C3: Region | D3: Product ID | E3: Quantity | F3: Unit Price | G3: Revenue | H3: Cost | I3: Tax | J3: Category
A4: T-1001 | B4: 46027 | C4: West | D4: P-107 | E4: 27 | F4: 365 | G4: 9855 | H4: 6615 | I4: =IF(G4-H4>0,(G4-H4)*Assumptions!B5,0) -> 648
A5: T-1002 | B5: 46029 | C5: East | D5: P-105 | E5: 13 | F5: 49 | G5: 637 | H5: 351 | I5: =IF(G5-H5>0,(G5-H5)*Assumptions!B6,0) -> 2860000
A6: T-1003 | B6: 46031 | C6: South | D6: P-105 | E6: 7 | F6: 49 | G6: 343 | H6: 189 | I6: =IF(G6-H6>0,(G6-H6)*Assumptions!B7,0) -> 38.5
A7: T-1004 | B7: 46033 | C7: North | D7: P-105 | E7: 5 | F7: 49 | G7: 245 | H7: 135 | I7: =IF(G7-H7>0,(G7-H7)*Assumptions!B8,0) -> 0
A8: T-1005 | B8: 46035 | C8: West | D8: P-101 | E8: 9 | F8: 890 | G8: 8010 | H8: 5580 | I8: =IF(G8-H8>0,(G8-H8)*Assumptions!B9,0) -> 0
A9: T-1006 | B9: 46037 | C9: East | D9: P-107 | E9: 28 | F9: 365 | G9: 10220 | H9: 6860 | I9: =IF(G9-H9>0,(G9-H9)*Assumptions!B10,0) -> 0
A10: T-1007 | B10: 46039 | C10: South | D10: P-107 | E10: 10 | F10: 365 | G10: 3650 | H10: 2450 | I10: =IF(G10-H10>0,(G10-H10)*Assumptions!B11,0) -> 0
A11: T-1008 | B11: 46041 | C11: North | D11: P-106 | E11: 22 | F11: 149 | G11: 3278 | H11: 1892 | I11: =IF(G11-H11>0,(G11-H11)*Assumptions!B12,0) -> 0
A12: T-1009 | B12: 46043 | C12: West | D12: P-107 | E12: 6 | F12: 365 | G12: 2190 | H12: 1470 | I12: =IF(G12-H12>0,(G12-H12)*Assumptions!B13,0) -> 0
A13: T-1010 | B13: 46045 | C13: East | D13: P-101 | E13: 6 | F13: 890 | G13: 5340 | H13: 3720 | I13: =IF(G13-H13>0,(G13-H13)*Assumptions!B14,0) -> 0
A14: T-1011 | B14: 46047 | C14: South | D14: P-104 | E14: 6 | F14: 95 | G14: 570 | H14: 348 | I14: =IF(G14-H14>0,(G14-H14)*Assumptions!B15,0) -> 0
A15: T-1012 | B15: 46049 | C15: North | D15: P-104 | E15: 12 | F15: 95 | G15: 1140 | H15: 696 | I15: =IF(G15-H15>0,(G15-H15)*Assumptions!B16,0) -> 0
... A33: T-1030 | B33: 46085 | C33: East | D33: P-103 | E33: 10 | F33: 295 | G33: 2950 | H33: 1900 | I33: =IF(G33-H33>0,(G33-H33)*Assumptions!B34,0) -> 0

Sheet Analysis
A1: Analysis — Repair the Model
A3: Metric | B3: Current formula / input | C3: Notes | E3: Dynamic output | F3: Formula / output
A4: Total Revenue | B4: =SUM(Sales!G4:G32) -> 153388 | C4: Currently excludes the final transaction. | E4: Sorted unique regions | F4: [enter SORT + UNIQUE formula]
A5: Rent Expense | B5: =B4*15% -> 23008.2 | C5: Currently uses a hard-coded 15% instead of the controlled assumption. | E5: High-value transaction filter | F5: [enter FILTER formula]
A6: North Revenue | B6: [complete] | C6: Complete with SUMIFS. | E6: Spill-range reference | F6: Use # to reference a dynamic result where appropriate
A7: High-Value Transactions | B7: [complete] | C7: Count Revenue above the threshold from Assumptions.
A8: Gross Profit | B8: =SUM(Sales!G4:G33)-SUM(Sales!H4:H33) -> 48918 | C8: Revenue minus Cost.
A9: Gross Margin | B9: =B8/B4 -> 0.31891673 | C9: Gross Profit / Total Revenue.
A10: Margin Status | B10: [rewrite with LET] | C10: Rewrite using LET and compare with Target Margin.
A13: Audit note: the workbook intentionally contains logical defects that can return valid-looking numbers. A repaired workbook should respond correctly when assumptions or transaction rows change.

Sheet Workbook Map
A1: Layer | B1: Sheet | C1: Purpose | D1: Student action
A2: Instructions | B2: START HERE | C2: Tasks and completion criteria | D2: Read
A3: Assumptions | B3: Assumptions | C3: Controlled model parameters | D3: Change only when testing
A4: Data | B4: Products | C4: Reference/master data | D4: Do not edit
A5: Data + calculations | B5: Sales | C5: Transactions and row-level calculations | D5: Repair Tax and Category
A6: Calculations / presentation | B6: Analysis | C6: KPIs and analytical outputs | D6: Complete and repair formulas
